{
  "en": {
    "header01": "Starters",
    "header02": "Noodles",
    "header03": "Sweets",
    "allergenLabel": "Allergens",
    "items": [
      {
        "cat": "starter",
        "name": "Kimchi",
        "price": 70,
        "ingredients": [
          "Jizo´s special homemade Kimchii"
        ],
        "allergens": {
          "hasGluten": false,
          "hasSoya": false,
          "hasFish": true,
          "hasOnion": true,
          "hasGarlic": true,
          "hasMushroom": false,
          "hasShellfish": true,
          "hasSesame": false,
          "hasNuts": false,
          "hasLemon": false,
          "hasLactose": false
        }
      },
      {
        "cat": "starter",
        "name": "Edamame",
        "price": 80,
        "ingredients": [
          "Yuzu Ponzu"
        ],
        "allergens": {
          "hasGluten": false,
          "hasSoya": true,
          "hasFish": false,
          "hasOnion": false,
          "hasGarlic": false,
          "hasMushroom": false,
          "hasShellfish": false,
          "hasSesame": false,
          "hasNuts": false,
          "hasLemon": true,
          "hasLactose": false
        }
      },
      {
        "name": "\"Mazemen\" Udon",
        "cat": "main",
        "price": 240,
        "ingredients": [
          "Homemade Noodles",
          "Creamy Pork Broth Tan Tan",
          "Pork Soboro",
          "Eggyolk",
          "Korn",
          "Bok Choi",
          "Scallion",
          "Infused Ginger-Oil"
        ],
        "allergens": {
          "hasGluten": true,
          "hasSoya": true,
          "hasFish": true,
          "hasOnion": true,
          "hasGarlic": true,
          "hasMushroom": true,
          "hasShellfish": false,
          "hasSesame": true,
          "hasNuts": false,
          "hasLemon": false,
          "hasLactose": false
        }
      },
      {
        "name": "Jizo Udon",
        "cat": "main",
        "price": 235,
        "ingredients": [
          "Homemade Noodles",
          "Flamed Chicken Breast ",
          "Classic Dashi",
          "Eggyolk",
          "Bok Choi",
          "Scallion",
          "Katsuobushi"
        ],
        "allergens": {
          "hasGluten": true,
          "hasSoya": true,
          "hasFish": true,
          "hasOnion": true,
          "hasGarlic": true,
          "hasMushroom": true,
          "hasShellfish": false,
          "hasSesame": false,
          "hasNuts": false,
          "hasLemon": true,
          "hasLactose": false
        }
      },
      {
        "name": "Umami Udon (Vegetarian) ",
        "cat": "main",
        "price": 235,
        "ingredients": [
          "Homemade Noodles",
          "Miso glazed Tempeh",
          "Mushroom Dashi",
          "Eggyolk",
          "Bok Choi",
          "Enoki",
          "Scallion",
          "Toasted Garlic Oil "
        ],
        "allergens": {
          "hasGluten": true,
          "hasSoya": true,
          "hasFish": false,
          "hasOnion": false,
          "hasGarlic": true,
          "hasMushroom": true,
          "hasShellfish": false,
          "hasSesame": false,
          "hasNuts": false,
          "hasLemon": true,
          "hasLactose": false
        }
      },
      {
        "cat": "main",
        "name": "\"Signature\" Shoyu Ramen",
        "price": 240,
        "ingredients": [
          "Homemade Tokyo style noodles",
          "Flamed Chicken Breast",
          "Chicken-pork Broth",
          "Ajitsuke-egg",
          "Slow baked Tomato",
          "Scallion"
        ],
        "allergens": {
          "hasGluten": true,
          "hasSoya": true,
          "hasFish": true,
          "hasOnion": false,
          "hasGarlic": true,
          "hasMushroom": true,
          "hasShellfish": false,
          "hasSesame": false,
          "hasNuts": false,
          "hasLemon": false,
          "hasLactose": false
        }
      },
      {
        "cat": "main",
        "name": "Shio Ramen",
        "price": 235,
        "ingredients": [
          "Homemade Tokyo style Noodles",
          "Flamed Chicken Breast ",
          "Chicken-pork Broth",
          "Ajitsuke-egg",
          "Pickled Bean Sprouts",
          "Enoki",
          "Scallion",
          "Aromatic Green Oil"
        ],
        "allergens": {
          "hasGluten": true,
          "hasSoya": true,
          "hasFish": false,
          "hasOnion": false,
          "hasGarlic": true,
          "hasMushroom": true,
          "hasShellfish": false,
          "hasSesame": false,
          "hasNuts": false,
          "hasLemon": false,
          "hasLactose": false
        }
      },
      {
        "name": "Yuzu Crème brûlée",
        "cat": "dessert",
        "price": 135,
        "ingredients": [
          "Bourbon Vanilla ",
          "Caramelized Sugar"
        ],
        "allergens": {
          "hasNuts": false,
          "hasGluten": false,
          "hasGarlic": false,
          "hasShellfish": false,
          "hasOnion": false,
          "hasFish": false,
          "hasSesame": false,
          "hasMushroom": false,
          "hasSoya": false,
          "hasLemon": true,
          "hasLactose": true
        }
      }
    ],
    "teaser01": ""
  },
  "no": {
    "header01": "test",
    "header02": "test",
    "teaser01": "test",
    "teaser02": "test",
    "allergenLabel": "test"
  }
}