{
  "en": {
    "header01": "Starters",
    "header02": "Noodles",
    "allergenLabel": "Allergens",
    "items": [
      {
        "cat": "starter",
        "name": "Kimchi",
        "price": 70,
        "ingredients": [
          "Jizo´s special homemade Kimchii"
        ],
        "allergens": {
          "hasNuts": false,
          "hasGluten": false,
          "hasGarlic": true,
          "hasShellfish": true,
          "hasOnion": true,
          "hasFish": true,
          "hasSesame": false,
          "hasMushroom": false,
          "hasLemon": false,
          "hasSoya": false
        }
      },
      {
        "cat": "starter",
        "name": "Edamame",
        "price": 80,
        "ingredients": [
          "Yuzu Ponzu"
        ],
        "allergens": {
          "hasNuts": false,
          "hasGluten": false,
          "hasGarlic": false,
          "hasShellfish": false,
          "hasOnion": false,
          "hasFish": false,
          "hasSesame": false,
          "hasMushroom": false,
          "hasLemon": true,
          "hasSoya": true
        }
      },
      {
        "cat": "starter",
        "name": "Nasu Dengaku",
        "price": 75,
        "ingredients": [
          "Aubergine",
          "Miso",
          "Sesame"
        ],
        "allergens": {
          "hasNuts": false,
          "hasGluten": true,
          "hasGarlic": false,
          "hasShellfish": false,
          "hasOnion": false,
          "hasFish": false,
          "hasSesame": true,
          "hasMushroom": false,
          "hasLemon": false,
          "hasSoya": true
        }
      },
      {
        "name": "\"Mazemen\" Udon",
        "cat": "main",
        "price": 240,
        "ingredients": [
          "Homemade Noodles",
          "Creamy Tonkotsu Tan Tan",
          "Pork Soboro",
          "Eggyolk",
          "Korn",
          "Pickled Bean Sprouts",
          "Scallion",
          "Black Garlic"
        ],
        "allergens": {
          "hasNuts": false,
          "hasGluten": true,
          "hasGarlic": true,
          "hasShellfish": false,
          "hasOnion": true,
          "hasFish": true,
          "hasSesame": true,
          "hasMushroom": true,
          "hasLemon": false,
          "hasSoya": true
        }
      },
      {
        "name": "Jizo Udon",
        "cat": "main",
        "price": 235,
        "ingredients": [
          "Homemade Noodles",
          "Slow cooked chicken Breast",
          "Classic Dashi",
          "Eggyolk",
          "Pok Choi",
          "Scallion",
          "Katsuobushi"
        ],
        "allergens": {
          "hasNuts": false,
          "hasGluten": true,
          "hasGarlic": true,
          "hasShellfish": false,
          "hasOnion": true,
          "hasFish": true,
          "hasSesame": false,
          "hasMushroom": true,
          "hasLemon": true,
          "hasSoya": true
        }
      },
      {
        "name": "Umami Udon (Vegetarian) ",
        "cat": "main",
        "price": 235,
        "ingredients": [
          "Homemade Noodles",
          "Baked Tempeh",
          "Mushroom Dashi",
          "Eggyolk",
          "Pok Choi",
          "Scallion",
          "Toasted Garlic Oil "
        ],
        "allergens": {
          "hasNuts": false,
          "hasGluten": true,
          "hasGarlic": true,
          "hasShellfish": false,
          "hasOnion": false,
          "hasFish": false,
          "hasSesame": false,
          "hasMushroom": true,
          "hasLemon": true,
          "hasSoya": true
        }
      },
      {
        "cat": "main",
        "name": "\"Signature\" Shoyu Ramen",
        "price": 240,
        "ingredients": [
          "Homemade Tokyo style noodles",
          "Flamed Chicken Breast",
          "Chicken-pork Broth",
          "Ajitsuke-egg",
          "Slow baked Tomato",
          "Scallion"
        ],
        "allergens": {
          "hasNuts": false,
          "hasGluten": true,
          "hasGarlic": true,
          "hasShellfish": false,
          "hasOnion": false,
          "hasFish": true,
          "hasSesame": false,
          "hasMushroom": true,
          "hasLemon": false,
          "hasSoya": true
        }
      },
      {
        "cat": "main",
        "name": "\"Thomas\" Shio Ramen",
        "price": 235,
        "ingredients": [
          "Homemade Tokyo style Noodles",
          "Flamed Chicken breast ",
          "Chicken-pork broth",
          "Ajitsuke-egg",
          "Scallion",
          "Pickled Bean Sprouts",
          "Aromatic Green Oil"
        ],
        "allergens": {
          "hasNuts": false,
          "hasGluten": true,
          "hasGarlic": true,
          "hasShellfish": false,
          "hasOnion": false,
          "hasFish": false,
          "hasSesame": false,
          "hasMushroom": true,
          "hasLemon": false,
          "hasSoya": true
        }
      }
    ]
  },
  "no": {
    "header01": "test",
    "header02": "test",
    "teaser01": "test",
    "teaser02": "test",
    "allergenLabel": "test"
  }
}